LICENSE
MANIFEST.in
README.md
pyproject.toml
setup.py
cpp_extension/vp_tree_bind.cpp
cpp_extension/vp_tree_q.hpp
infinitysearch/__init__.py
infinitysearch/ann.py
infinitysearch/fermat.py
infinitysearch/main.py
infinitysearch/models.py
infinitysearch/test.py
infinitysearch/utils.py
infinitysearch.egg-info/PKG-INFO
infinitysearch.egg-info/SOURCES.txt
infinitysearch.egg-info/dependency_links.txt
infinitysearch.egg-info/requires.txt
infinitysearch.egg-info/top_level.txt