Metadata-Version: 2.4
Name: infinitysearch
Version: 0.1.0
Summary: Fermat-based approximate nearest neighbor search with VP-tree backend
Author: Antonio Pariente
License: CC-BY-NC-SA-4.0
Classifier: Programming Language :: Python :: 3
Classifier: Operating System :: OS Independent
Requires-Python: >=3.9
License-File: LICENSE
Requires-Dist: numpy
Requires-Dist: scipy
Requires-Dist: torch
Requires-Dist: tensorflow
Requires-Dist: scikit-learn
Requires-Dist: pybind11
Requires-Dist: optuna
Dynamic: author
Dynamic: classifier
Dynamic: description
Dynamic: description-content-type
Dynamic: license
Dynamic: license-file
Dynamic: requires-dist
Dynamic: requires-python
Dynamic: summary
